fofa_py/__init__.py
fofa_py/factory.py
fofa_py/basic/__init__.py
fofa_py/basic/etc.py
fofa_py/basic/exceptions.py
fofa_py/util/__init__.py
fofa_py/util/cache.py
fofa_py/util/query.py
python_fofa_sy-1.2.3.dist-info/LICENSE
python_fofa_sy-1.2.3.dist-info/METADATA
python_fofa_sy-1.2.3.dist-info/WHEEL
python_fofa_sy-1.2.3.dist-info/top_level.txt
python_fofa_sy-1.2.3.dist-info/RECORD
