Metadata-Version: 2.1
Name: python-fofa-sy
Version: 1.2.3
Summary: Fofa引擎的Python接口 | A Python api for fofa assets-scan engine
Author-email: SyYhunfhds MemorySeer <syyhunfhdsmemoryseer@gmail.com>
License: MIT License
Project-URL: Homepage, https://github.com/SyYhunfhds-s-House/python-fofa-sy
Project-URL: Bug Tracker, https://github.com/SyYhunfhds-s-House/python-fofa-sy/issues
Project-URL: Repository, https://github.com/SyYhunfhds-s-House/python-fofa-sy
Requires-Python: >=3.7
License-File: LICENSE
Requires-Dist: babel >=2.14.0
Requires-Dist: cachetools >=5.2.0
Requires-Dist: loguru >=0.7.3
Requires-Dist: requests >=2.31.0
Requires-Dist: tablib >=3.4.0
